serverj/__init__.py
serverj/core.py
serverj-0.1.dist-info/METADATA
serverj-0.1.dist-info/WHEEL
serverj-0.1.dist-info/top_level.txt
serverj-0.1.dist-info/RECORD
