Metadata-Version: 2.1
Name: serverj
Version: 0.1
Summary: A simple library for simple, random tasks
Home-page: https://example.com
Author: YeetboiRJL
Author-email: yeetboirjl@hotmail.com
License: YeetboiRJL
Requires-Python: >=3.6
Requires-Dist: numpy>=1.20
